extra_requirements/gcs.txt
extra_requirements/mlflow.txt
extra_requirements/roboflow.txt
extra_requirements/s3.txt
luxonis_ml/__init__.py
luxonis_ml/__main__.py
luxonis_ml/guard_extras.py
luxonis_ml/typing.py
luxonis_ml/data/__init__.py
luxonis_ml/data/__main__.py
luxonis_ml/data/requirements.txt
luxonis_ml/data/augmentations/__init__.py
luxonis_ml/data/augmentations/albumentations_engine.py
luxonis_ml/data/augmentations/base_engine.py
luxonis_ml/data/augmentations/batch_compose.py
luxonis_ml/data/augmentations/batch_transform.py
luxonis_ml/data/augmentations/utils.py
luxonis_ml/data/augmentations/custom/__init__.py
luxonis_ml/data/augmentations/custom/letterbox_resize.py
luxonis_ml/data/augmentations/custom/mixup.py
luxonis_ml/data/augmentations/custom/mosaic.py
luxonis_ml/data/augmentations/custom/symetric_keypoints_flip.py
luxonis_ml/data/datasets/__init__.py
luxonis_ml/data/datasets/annotation.py
luxonis_ml/data/datasets/base_dataset.py
luxonis_ml/data/datasets/luxonis_dataset.py
luxonis_ml/data/datasets/metadata.py
luxonis_ml/data/datasets/migration.py
luxonis_ml/data/datasets/source.py
luxonis_ml/data/datasets/utils.py
luxonis_ml/data/loaders/__init__.py
luxonis_ml/data/loaders/base_loader.py
luxonis_ml/data/loaders/luxonis_loader.py
luxonis_ml/data/parsers/__init__.py
luxonis_ml/data/parsers/base_parser.py
luxonis_ml/data/parsers/classification_directory_parser.py
luxonis_ml/data/parsers/coco_parser.py
luxonis_ml/data/parsers/create_ml_parser.py
luxonis_ml/data/parsers/darknet_parser.py
luxonis_ml/data/parsers/luxonis_parser.py
luxonis_ml/data/parsers/native_parser.py
luxonis_ml/data/parsers/segmentation_mask_directory_parser.py
luxonis_ml/data/parsers/solo_parser.py
luxonis_ml/data/parsers/tensorflow_csv_parser.py
luxonis_ml/data/parsers/voc_parser.py
luxonis_ml/data/parsers/yolov4_parser.py
luxonis_ml/data/parsers/yolov6_parser.py
luxonis_ml/data/parsers/yolov8_parser.py
luxonis_ml/data/utils/__init__.py
luxonis_ml/data/utils/constants.py
luxonis_ml-0.8.1.dist-info/licenses/LICENSE
luxonis_ml-0.8.1.dist-info/METADATA
luxonis_ml-0.8.1.dist-info/WHEEL
luxonis_ml-0.8.1.dist-info/entry_points.txt
luxonis_ml-0.8.1.dist-info/top_level.txt
luxonis_ml-0.8.1.dist-info/RECORD
