Metadata-Version: 2.4
Name: luxonis-ml
Version: 0.8.1
Summary: MLOps tools for training models for Luxonis devices
Author-email: Luxonis <support@luxonis.com>
Maintainer-email: Luxonis <support@luxonis.com>
License:                                  Apache License
Project-URL: repository, https://github.com/luxonis/luxonis-ml
Project-URL: issues, https://github.com/luxonis/luxonis-ml/issues
Keywords: ml,ops,camera,luxonis,oak
Classifier: License :: OSI Approved :: Apache Software License
Classifier: Development Status :: 4 - Beta
Classifier: Programming Language :: Python :: 3.10
Classifier: Topic :: Scientific/Engineering :: Artificial Intelligence
Classifier: Topic :: Scientific/Engineering :: Image Processing
Classifier: Topic :: Scientific/Engineering :: Image Recognition
Requires-Python: >=3.10
License-File: LICENSE
Requires-Dist: pydantic~=2.7
Requires-Dist: pydantic-extra-types~=2.10
Requires-Dist: pydantic-settings~=2.1
Requires-Dist: PyYAML~=6.0
Requires-Dist: fsspec>=2023.3.0
Requires-Dist: rich~=13.6
Requires-Dist: semver~=3.0
Requires-Dist: typer~=0.12
Requires-Dist: typeguard~=4.1
Requires-Dist: aiobotocore<2.18
Requires-Dist: loguru~=0.7
Provides-Extra: data
Requires-Dist: numpy~=1.22; extra == "data"
Requires-Dist: opencv-python~=4.10; extra == "data"
Requires-Dist: albumentations>=2.0.0; extra == "data"
Requires-Dist: pyarrow~=17.0; extra == "data"
Requires-Dist: pycocotools~=2.0; extra == "data"
Requires-Dist: polars[timezone]~=0.20; extra == "data"
Requires-Dist: ordered-set~=4.0; extra == "data"
Requires-Dist: semver~=3.0; extra == "data"
Requires-Dist: filelock~=3.0; extra == "data"
Requires-Dist: bidict~=0.21; extra == "data"
Requires-Dist: gdown~=4.7; extra == "data"
Requires-Dist: defusedxml~=0.7; extra == "data"
Requires-Dist: pillow-heif<0.22.0; extra == "data"
Requires-Dist: matplotlib~=3.10; extra == "data"
Provides-Extra: utils
Requires-Dist: pydantic~=2.7; extra == "utils"
Requires-Dist: pydantic-extra-types~=2.10; extra == "utils"
Requires-Dist: pydantic-settings~=2.1; extra == "utils"
Requires-Dist: PyYAML~=6.0; extra == "utils"
Requires-Dist: fsspec>=2023.3.0; extra == "utils"
Requires-Dist: rich~=13.6; extra == "utils"
Requires-Dist: semver~=3.0; extra == "utils"
Requires-Dist: typer~=0.12; extra == "utils"
Requires-Dist: typeguard~=4.1; extra == "utils"
Requires-Dist: aiobotocore<2.18; extra == "utils"
Requires-Dist: loguru~=0.7; extra == "utils"
Provides-Extra: tracker
Requires-Dist: unique-names-generator>=1.0.2; extra == "tracker"
Requires-Dist: numpy>=1.22; extra == "tracker"
Provides-Extra: nn-archive
Requires-Dist: pydantic~=2.7; extra == "nn-archive"
Requires-Dist: pydantic-settings~=2.1; extra == "nn-archive"
Provides-Extra: roboflow
Requires-Dist: roboflow~=1.1.0; extra == "roboflow"
Provides-Extra: gcs
Requires-Dist: gcsfs>=2023.3.0; extra == "gcs"
Provides-Extra: s3
Requires-Dist: s3fs>=2023.3.0; extra == "s3"
Provides-Extra: mlflow
Requires-Dist: mlflow~=3.1; extra == "mlflow"
Provides-Extra: all
Requires-Dist: numpy~=1.22; extra == "all"
Requires-Dist: opencv-python~=4.10; extra == "all"
Requires-Dist: albumentations>=2.0.0; extra == "all"
Requires-Dist: pyarrow~=17.0; extra == "all"
Requires-Dist: pycocotools~=2.0; extra == "all"
Requires-Dist: polars[timezone]~=0.20; extra == "all"
Requires-Dist: ordered-set~=4.0; extra == "all"
Requires-Dist: semver~=3.0; extra == "all"
Requires-Dist: filelock~=3.0; extra == "all"
Requires-Dist: bidict~=0.21; extra == "all"
Requires-Dist: gdown~=4.7; extra == "all"
Requires-Dist: defusedxml~=0.7; extra == "all"
Requires-Dist: pillow-heif<0.22.0; extra == "all"
Requires-Dist: matplotlib~=3.10; extra == "all"
Requires-Dist: pydantic~=2.7; extra == "all"
Requires-Dist: pydantic-extra-types~=2.10; extra == "all"
Requires-Dist: pydantic-settings~=2.1; extra == "all"
Requires-Dist: PyYAML~=6.0; extra == "all"
Requires-Dist: fsspec>=2023.3.0; extra == "all"
Requires-Dist: rich~=13.6; extra == "all"
Requires-Dist: semver~=3.0; extra == "all"
Requires-Dist: typer~=0.12; extra == "all"
Requires-Dist: typeguard~=4.1; extra == "all"
Requires-Dist: aiobotocore<2.18; extra == "all"
Requires-Dist: loguru~=0.7; extra == "all"
Requires-Dist: unique-names-generator>=1.0.2; extra == "all"
Requires-Dist: numpy>=1.22; extra == "all"
Requires-Dist: pydantic~=2.7; extra == "all"
Requires-Dist: pydantic-settings~=2.1; extra == "all"
Requires-Dist: roboflow~=1.1.0; extra == "all"
Requires-Dist: gcsfs>=2023.3.0; extra == "all"
Requires-Dist: s3fs>=2023.3.0; extra == "all"
Requires-Dist: mlflow~=3.1; extra == "all"
Provides-Extra: dev
Requires-Dist: numpy~=1.22; extra == "dev"
Requires-Dist: opencv-python~=4.10; extra == "dev"
Requires-Dist: albumentations>=2.0.0; extra == "dev"
Requires-Dist: pyarrow~=17.0; extra == "dev"
Requires-Dist: pycocotools~=2.0; extra == "dev"
Requires-Dist: polars[timezone]~=0.20; extra == "dev"
Requires-Dist: ordered-set~=4.0; extra == "dev"
Requires-Dist: semver~=3.0; extra == "dev"
Requires-Dist: filelock~=3.0; extra == "dev"
Requires-Dist: bidict~=0.21; extra == "dev"
Requires-Dist: gdown~=4.7; extra == "dev"
Requires-Dist: defusedxml~=0.7; extra == "dev"
Requires-Dist: pillow-heif<0.22.0; extra == "dev"
Requires-Dist: matplotlib~=3.10; extra == "dev"
Requires-Dist: pydantic~=2.7; extra == "dev"
Requires-Dist: pydantic-extra-types~=2.10; extra == "dev"
Requires-Dist: pydantic-settings~=2.1; extra == "dev"
Requires-Dist: PyYAML~=6.0; extra == "dev"
Requires-Dist: fsspec>=2023.3.0; extra == "dev"
Requires-Dist: rich~=13.6; extra == "dev"
Requires-Dist: semver~=3.0; extra == "dev"
Requires-Dist: typer~=0.12; extra == "dev"
Requires-Dist: typeguard~=4.1; extra == "dev"
Requires-Dist: aiobotocore<2.18; extra == "dev"
Requires-Dist: loguru~=0.7; extra == "dev"
Requires-Dist: unique-names-generator>=1.0.2; extra == "dev"
Requires-Dist: numpy>=1.22; extra == "dev"
Requires-Dist: pydantic~=2.7; extra == "dev"
Requires-Dist: pydantic-settings~=2.1; extra == "dev"
Requires-Dist: roboflow~=1.1.0; extra == "dev"
Requires-Dist: gcsfs>=2023.3.0; extra == "dev"
Requires-Dist: s3fs>=2023.3.0; extra == "dev"
Requires-Dist: mlflow~=3.1; extra == "dev"
Requires-Dist: pre-commit<4.0.0; extra == "dev"
Requires-Dist: pytest-cov>=4.1.0; extra == "dev"
Requires-Dist: pytest-dependency>=0.6.0; extra == "dev"
Requires-Dist: pytest-subtests>=0.12.1; extra == "dev"
Requires-Dist: pytest-xdist>=3.6.0; extra == "dev"
Requires-Dist: onnx<1.17.0; extra == "dev"
Requires-Dist: roboflow>=1.0.0; extra == "dev"
Dynamic: license-file
